{
  "title": "Security Whitepaper for Tool_1",
  "sections": [
    {
      "title": "Introduction",
      "subsections": [
        {
          "title": "Purpose of the Document"
        },
        {
          "title": "Overview of Tool_1"
        },
        {
          "title": "Intended Audience"
        }
      ]
    },
    {
      "title": "Security Framework",
      "subsections": [
        {
          "title": "Core Principles",
          "subsections": [
            {
              "title": "Confidentiality"
            },
            {
              "title": "Integrity"
            },
            {
              "title": "Availability"
            }
          ]
        },
        {
          "title": "Compliance Standards",
          "subsections": [
            {
              "title": "GDPR"
            },
            {
              "title": "ISO/IEC 27001"
            },
            {
              "title": "NIST Cybersecurity Framework"
            }
          ]
        }
      ]
    },
    {
      "title": "Threat Detection and Mitigation",
      "subsections": [
        {
          "title": "AI-Driven Threat Detection"
        },
        {
          "title": "Vulnerability Assessment Process"
        },
        {
          "title": "Incident Response Protocols"
        }
      ]
    },
    {
      "title": "Secure Model Deployment",
      "subsections": [
        {
          "title": "Deployment Best Practices"
        },
        {
          "title": "Encryption and Key Management"
        },
        {
          "title": "Access Control Mechanisms"
        }
      ]
    },
    {
      "title": "Data Security",
      "subsections": [
        {
          "title": "Data Encryption Standards"
        },
        {
          "title": "Secure Data Transmission"
        },
        {
          "title": "Data Storage Policies"
        }
      ]
    },
    {
      "title": "Risk Management",
      "subsections": [
        {
          "title": "Risk Assessment Methodology"
        },
        {
          "title": "Continuous Monitoring"
        },
        {
          "title": "Remediation Strategies"
        }
      ]
    },
    {
      "title": "Compliance and Certification",
      "subsections": [
        {
          "title": "Auditing Processes"
        },
        {
          "title": "Third-Party Certifications"
        },
        {
          "title": "Ongoing Compliance Efforts"
        }
      ]
    },
    {
      "title": "Conclusion",
      "subsections": [
        {
          "title": "Summary of Security Measures"
        },
        {
          "title": "Commitment to Security"
        },
        {
          "title": "Future Enhancements"
        }
      ]
    },
    {
      "title": "Appendices",
      "subsections": [
        {
          "title": "Glossary of Terms"
        },
        {
          "title": "References"
        },
        {
          "title": "Contact Information"
        }
      ]
    }
  ]
}